{
  "HALProvider": {
    "Other Devices": {
      "SPARK MAX [3] ALTERNATE ENCODER": {
        "header": {
          "open": true
        }
      }
    }
  },
  "NTProvider": {
    "types": {
      "/FMSInfo": "FMSInfo",
      "/SmartDashboard/Arm": "Mechanism2d",
      "/SmartDashboard/Autonomous": "String Chooser",
      "/SmartDashboard/SimArm": "Mechanism2d"
    },
    "windows": {
      "/SmartDashboard/Autonomous": {
        "window": {
          "visible": true
        }
      },
      "/SmartDashboard/SimArm": {
        "window": {
          "visible": true
        }
      }
    }
  },
  "NetworkTables": {
    "retained": {
      "SmartDashboard": {
        "open": true
      }
    },
    "transitory": {
      "Shuffleboard": {
        "open": true
      },
      "SmartDashboard": {
        "Arm": {
          "double[]##v_/SmartDashboard/Arm/dims": {
            "open": true
          },
          "open": true
        },
        "SimArm": {
          "open": true
        },
        "open": true
      }
    }
  },
  "NetworkTables Info": {
    "Clients": {
      "open": true
    },
    "Connections": {
      "open": true
    },
    "Server": {
      "open": true
    },
    "visible": true
  },
  "Plot": {
    "Plot <0>": {
      "plots": [
        {
          "backgroundColor": [
            0.0,
            0.0,
            0.0,
            0.8500000238418579
          ],
          "height": 338
        }
      ]
    }
  }
}
